_vhc_pybinds.cpython-38-darwin.so
_core_pybinds.cpython-38-darwin.so
projectaria_vrs_health_check/run_vrs_health_check.py
projectaria_vrs_health_check/vrs_health_check.py
projectaria_vrs_health_check/__init__.py
projectaria_vrs_health_check/.dylibs/libturbojpeg.0.4.0.dylib
projectaria_vrs_health_check/.dylibs/libboost_iostreams.dylib
projectaria_vrs_health_check/.dylibs/liblz4.1.10.0.dylib
projectaria_vrs_health_check/.dylibs/libavformat.61.7.100.dylib
projectaria_vrs_health_check/.dylibs/libicudata.77.1.dylib
projectaria_vrs_health_check/.dylibs/libavcodec.61.19.100.dylib
projectaria_vrs_health_check/.dylibs/libX11.6.dylib
projectaria_vrs_health_check/.dylibs/libpng16.16.dylib
projectaria_vrs_health_check/.dylibs/libicuuc.77.1.dylib
projectaria_vrs_health_check/.dylibs/libfmt.11.2.0.dylib
projectaria_vrs_health_check/.dylibs/libboost_random.dylib
projectaria_vrs_health_check/.dylibs/libxcb.1.1.0.dylib
projectaria_vrs_health_check/.dylibs/libboost_regex.dylib
projectaria_vrs_health_check/.dylibs/libXdmcp.6.dylib
projectaria_vrs_health_check/.dylibs/libavutil.59.39.100.dylib
projectaria_vrs_health_check/.dylibs/libXau.6.dylib
projectaria_vrs_health_check/.dylibs/libboost_filesystem.dylib
projectaria_vrs_health_check/.dylibs/liblzma.5.dylib
projectaria_vrs_health_check/.dylibs/libjpeg.8.3.2.dylib
projectaria_vrs_health_check/.dylibs/libboost_atomic.dylib
projectaria_vrs_health_check/.dylibs/libboost_date_time.dylib
projectaria_vrs_health_check/.dylibs/libxxhash.0.8.3.dylib
projectaria_vrs_health_check/.dylibs/libicui18n.77.1.dylib
projectaria_vrs_health_check/.dylibs/libzstd.1.5.7.dylib
projectaria_vrs_health_check/.dylibs/libopus.0.dylib
projectaria_vrs_health_check-1.1.0.dist-info/RECORD
projectaria_vrs_health_check-1.1.0.dist-info/WHEEL
projectaria_vrs_health_check-1.1.0.dist-info/entry_points.txt
projectaria_vrs_health_check-1.1.0.dist-info/top_level.txt
projectaria_vrs_health_check-1.1.0.dist-info/METADATA
