Metadata-Version: 2.1
Name: projectaria-vrs-health-check
Version: 1.1.0
Summary: Project Aria Vrs Health Check tool
Home-page: https://github.com/facebookresearch/projectaria_tools
Author: Meta Reality Labs Research
License: Apache-2.0
Requires-Python: >=3.8
Requires-Dist: numpy
